owl/__init__.py
owl/audio_scale.py
owl/converters/__init__.py
owl/converters/base.py
owl/converters/dynamic/__init__.py
owl/converters/dynamic/base.py
owl/converters/dynamic/scan.py
owl/converters/focus.py
owl/converters/static/__init__.py
owl/converters/static/base.py
owl/converters/static/curve.py
owl/converters/static/spread.py
owl/converters/utils.py
owl/curves.py
owl/events.py
owl/scripts/owl.py
owl/soundgen.py
owl/types.py
owl_framework-0.1.1.dist-info/entry_points.txt
owl_framework-0.1.1.dist-info/LICENSE
owl_framework-0.1.1.dist-info/METADATA
owl_framework-0.1.1.dist-info/WHEEL
owl_framework-0.1.1.dist-info/RECORD
